girder_client/__init__.py
girder_client/cli.py
girder_client-5.0.0a14.dev27.dist-info/METADATA
girder_client-5.0.0a14.dev27.dist-info/WHEEL
girder_client-5.0.0a14.dev27.dist-info/entry_points.txt
girder_client-5.0.0a14.dev27.dist-info/top_level.txt
girder_client-5.0.0a14.dev27.dist-info/RECORD
